AUTHORS
LICENSE
MANIFEST.in
README.rst
pyproject.toml
setup.cfg
setup.py
django_y_message.egg-info/PKG-INFO
django_y_message.egg-info/SOURCES.txt
django_y_message.egg-info/dependency_links.txt
django_y_message.egg-info/requires.txt
django_y_message.egg-info/top_level.txt
ymessage/__init__.py
ymessage/admin.py
ymessage/apps.py
ymessage/models.py
ymessage/service.py
ymessage/tests.py
ymessage/urls.py
ymessage/views.py
ymessage/migrations/0001_initial.py
ymessage/migrations/__init__.py