Metadata-Version: 2.1
Name: django-y-message
Version: 1.0.0
Summary: Ymessage is a Django app to implement **Transactional Outbox** pattern(https://microservices.io/patterns/data/transactional-outbox.html).
Home-page: https://github.com/zyunx/django-y-message
Author: Zhang Yun
Author-email: zyunx.net@gmail.com
License: BSD-3-Clause
Classifier: Environment :: Web Environment
Classifier: Framework :: Django
Classifier: Framework :: Django :: 4.0
Classifier: Intended Audience :: Developers
Classifier: License :: OSI Approved :: BSD License
Classifier: Operating System :: OS Independent
Classifier: Programming Language :: Python
Classifier: Programming Language :: Python :: 3
Classifier: Programming Language :: Python :: 3.8
Classifier: Programming Language :: Python :: 3.9
Requires-Python: >=3.8
License-File: LICENSE
License-File: AUTHORS
